AUTHORS
CHANGELOG.txt
DESCRIPTION
LICENSE
MANIFEST.in
README.rst
setup.py
cmsplugin_pdf/__init__.py
cmsplugin_pdf/admin.py
cmsplugin_pdf/cms_plugins.py
cmsplugin_pdf/models.py
cmsplugin_pdf/settings.py
cmsplugin_pdf.egg-info/PKG-INFO
cmsplugin_pdf.egg-info/SOURCES.txt
cmsplugin_pdf.egg-info/dependency_links.txt
cmsplugin_pdf.egg-info/requires.txt
cmsplugin_pdf.egg-info/top_level.txt
cmsplugin_pdf/migrations/0001_initial.py
cmsplugin_pdf/migrations/0002_auto__add_field_pdfpluginmodel_display_type.py
cmsplugin_pdf/migrations/__init__.py
cmsplugin_pdf/templates/base.html
cmsplugin_pdf/templates/standard.html
cmsplugin_pdf/templates/cmsplugin_pdf/partials/pdf.html
cmsplugin_pdf/templatetags/__init__.py
cmsplugin_pdf/templatetags/cmsplugin_pdf_tags.py
cmsplugin_pdf/tests/__init__.py
cmsplugin_pdf/tests/cmsplugin_pdf_tags_tests.py
cmsplugin_pdf/tests/cmsplugin_tests.py
cmsplugin_pdf/tests/factories.py
cmsplugin_pdf/tests/models_tests.py
cmsplugin_pdf/tests/runtests.py
cmsplugin_pdf/tests/south_settings.py
cmsplugin_pdf/tests/test_settings.py
cmsplugin_pdf/tests/urls.py
cmsplugin_pdf/tests/test_files/Lose away.pdf