Metadata-Version: 1.0
Name: cmsplugin-pdf
Version: 0.5.1
Summary: A reusable Django app to add PDFs to Django-CMS.
